{
  "type": "Program",
  "body": [
    {
      "type": "ImportDeclaration",
      "specifiers": [
        {
          "type": "ImportDefaultSpecifier",
          "local": {
            "type": "Identifier",
            "name": "pointwise2",
            "range": [
              8,
              18
            ],
            "loc": {
              "start": {
                "line": 2,
                "column": 7
              },
              "end": {
                "line": 2,
                "column": 17
              }
            }
          },
          "range": [
            8,
            18
          ],
          "loc": {
            "start": {
              "line": 2,
              "column": 7
            },
            "end": {
              "line": 2,
              "column": 17
            }
          }
        }
      ],
      "source": {
        "type": "Literal",
        "value": "./pointwise2",
        "raw": "'./pointwise2'",
        "range": [
          24,
          38
        ],
        "loc": {
          "start": {
            "line": 2,
            "column": 23
          },
          "end": {
            "line": 2,
            "column": 37
          }
        },
        "trailingComments": [
          {
            "type": "Block",
            "value": "*\n * Pointwise Math.pow(x, y)\n * \n * @export\n * @param {Number|Array|Complex|Sparse} m1\n * @param {Number|Array|Complex|Sparse} m2\n * @returns {Number|Array|Complex|Sparse}\n * @example \n * \n * pow(1, 2)\n * // returns Math.pow(1, 2)\n * pow([1, 2], [2, 2])\n * // returns [Math.pow(1, 2), Math.pow(2, 2)]\n * pow([[2,1], [1,2]], [[2, 2], [2, 2]]))\n * // returns [ [Math.pow(2, 2), Math.pow(1, 2)], [Math.pow(1, 2), Math.pow(2, 2)] ]\n ",
            "range": [
              40,
              474
            ],
            "loc": {
              "start": {
                "line": 4,
                "column": 0
              },
              "end": {
                "line": 19,
                "column": 3
              }
            }
          }
        ]
      },
      "range": [
        1,
        475
      ],
      "loc": {
        "start": {
          "line": 2,
          "column": 0
        },
        "end": {
          "line": 20,
          "column": 0
        }
      }
    },
    {
      "type": "ExportDefaultDeclaration",
      "declaration": {
        "type": "FunctionDeclaration",
        "id": null,
        "params": [
          {
            "type": "Identifier",
            "name": "m1",
            "range": [
              500,
              502
            ],
            "loc": {
              "start": {
                "line": 20,
                "column": 25
              },
              "end": {
                "line": 20,
                "column": 27
              }
            }
          },
          {
            "type": "Identifier",
            "name": "m2",
            "range": [
              504,
              506
            ],
            "loc": {
              "start": {
                "line": 20,
                "column": 29
              },
              "end": {
                "line": 20,
                "column": 31
              }
            }
          }
        ],
        "body": {
          "type": "BlockStatement",
          "body": [
            {
              "type": "ReturnStatement",
              "argument": {
                "type": "CallExpression",
                "callee": {
                  "type": "CallExpression",
                  "callee": {
                    "type": "Identifier",
                    "name": "pointwise2",
                    "range": [
                      520,
                      530
                    ],
                    "loc": {
                      "start": {
                        "line": 21,
                        "column": 9
                      },
                      "end": {
                        "line": 21,
                        "column": 19
                      }
                    }
                  },
                  "arguments": [
                    {
                      "type": "MemberExpression",
                      "computed": false,
                      "object": {
                        "type": "Identifier",
                        "name": "Math",
                        "range": [
                          531,
                          535
                        ],
                        "loc": {
                          "start": {
                            "line": 21,
                            "column": 20
                          },
                          "end": {
                            "line": 21,
                            "column": 24
                          }
                        }
                      },
                      "property": {
                        "type": "Identifier",
                        "name": "pow",
                        "range": [
                          536,
                          539
                        ],
                        "loc": {
                          "start": {
                            "line": 21,
                            "column": 25
                          },
                          "end": {
                            "line": 21,
                            "column": 28
                          }
                        }
                      },
                      "range": [
                        531,
                        539
                      ],
                      "loc": {
                        "start": {
                          "line": 21,
                          "column": 20
                        },
                        "end": {
                          "line": 21,
                          "column": 28
                        }
                      }
                    }
                  ],
                  "range": [
                    520,
                    540
                  ],
                  "loc": {
                    "start": {
                      "line": 21,
                      "column": 9
                    },
                    "end": {
                      "line": 21,
                      "column": 29
                    }
                  }
                },
                "arguments": [
                  {
                    "type": "Identifier",
                    "name": "m1",
                    "range": [
                      541,
                      543
                    ],
                    "loc": {
                      "start": {
                        "line": 21,
                        "column": 30
                      },
                      "end": {
                        "line": 21,
                        "column": 32
                      }
                    }
                  },
                  {
                    "type": "Identifier",
                    "name": "m2",
                    "range": [
                      545,
                      547
                    ],
                    "loc": {
                      "start": {
                        "line": 21,
                        "column": 34
                      },
                      "end": {
                        "line": 21,
                        "column": 36
                      }
                    }
                  }
                ],
                "range": [
                  520,
                  548
                ],
                "loc": {
                  "start": {
                    "line": 21,
                    "column": 9
                  },
                  "end": {
                    "line": 21,
                    "column": 37
                  }
                }
              },
              "range": [
                513,
                549
              ],
              "loc": {
                "start": {
                  "line": 21,
                  "column": 2
                },
                "end": {
                  "line": 22,
                  "column": 0
                }
              }
            }
          ],
          "range": [
            508,
            550
          ],
          "loc": {
            "start": {
              "line": 20,
              "column": 33
            },
            "end": {
              "line": 22,
              "column": 1
            }
          }
        },
        "generator": false,
        "expression": false,
        "range": [
          490,
          550
        ],
        "loc": {
          "start": {
            "line": 20,
            "column": 15
          },
          "end": {
            "line": 22,
            "column": 1
          }
        },
        "leadingComments": [
          {
            "type": "Block",
            "value": "*\n * Pointwise Math.pow(x, y)\n * \n * @export\n * @param {Number|Array|Complex|Sparse} m1\n * @param {Number|Array|Complex|Sparse} m2\n * @returns {Number|Array|Complex|Sparse}\n * @example \n * \n * pow(1, 2)\n * // returns Math.pow(1, 2)\n * pow([1, 2], [2, 2])\n * // returns [Math.pow(1, 2), Math.pow(2, 2)]\n * pow([[2,1], [1,2]], [[2, 2], [2, 2]]))\n * // returns [ [Math.pow(2, 2), Math.pow(1, 2)], [Math.pow(1, 2), Math.pow(2, 2)] ]\n ",
            "range": [
              40,
              474
            ],
            "loc": {
              "start": {
                "line": 4,
                "column": 0
              },
              "end": {
                "line": 19,
                "column": 3
              }
            }
          }
        ],
        "trailingComments": []
      },
      "range": [
        475,
        550
      ],
      "loc": {
        "start": {
          "line": 20,
          "column": 0
        },
        "end": {
          "line": 22,
          "column": 1
        }
      },
      "leadingComments": [
        {
          "type": "Block",
          "value": "*\n * Pointwise Math.pow(x, y)\n * \n * @export\n * @param {Number|Array|Complex|Sparse} m1\n * @param {Number|Array|Complex|Sparse} m2\n * @returns {Number|Array|Complex|Sparse}\n * @example \n * \n * pow(1, 2)\n * // returns Math.pow(1, 2)\n * pow([1, 2], [2, 2])\n * // returns [Math.pow(1, 2), Math.pow(2, 2)]\n * pow([[2,1], [1,2]], [[2, 2], [2, 2]]))\n * // returns [ [Math.pow(2, 2), Math.pow(1, 2)], [Math.pow(1, 2), Math.pow(2, 2)] ]\n ",
          "range": [
            40,
            474
          ],
          "loc": {
            "start": {
              "line": 4,
              "column": 0
            },
            "end": {
              "line": 19,
              "column": 3
            }
          }
        }
      ]
    }
  ],
  "sourceType": "module",
  "range": [
    1,
    550
  ],
  "loc": {
    "start": {
      "line": 2,
      "column": 0
    },
    "end": {
      "line": 22,
      "column": 1
    }
  },
  "comments": [
    {
      "type": "Block",
      "value": "*\n * Pointwise Math.pow(x, y)\n * \n * @export\n * @param {Number|Array|Complex|Sparse} m1\n * @param {Number|Array|Complex|Sparse} m2\n * @returns {Number|Array|Complex|Sparse}\n * @example \n * \n * pow(1, 2)\n * // returns Math.pow(1, 2)\n * pow([1, 2], [2, 2])\n * // returns [Math.pow(1, 2), Math.pow(2, 2)]\n * pow([[2,1], [1,2]], [[2, 2], [2, 2]]))\n * // returns [ [Math.pow(2, 2), Math.pow(1, 2)], [Math.pow(1, 2), Math.pow(2, 2)] ]\n ",
      "range": [
        40,
        474
      ],
      "loc": {
        "start": {
          "line": 4,
          "column": 0
        },
        "end": {
          "line": 19,
          "column": 3
        }
      }
    }
  ]
}